<?xml version="1.0" encoding="utf-8"?>
<LanguageData>
  <!--The following translations were generated by https://www.deepl.com/-->
  <MFM_ReturnPrisonedMercs>被囚禁的雇佣兵</MFM_ReturnPrisonedMercs>
  <MFM_AddPrisonerMerc>添加被囚禁的雇佣兵</MFM_AddPrisonerMerc>
  <MFM_RemovePrisonerMerc>删除囚犯</MFM_RemovePrisonerMerc>
  <MFM_HealthImpacted>( -{0} 降低健康值 )</MFM_HealthImpacted>
  <MFM_RandomRace>随机种族</MFM_RandomRace>
  <MFM_BuyMerc>购买雇佣兵</MFM_BuyMerc>
  <MFM_SlaveMercenary>奴隶佣兵</MFM_SlaveMercenary>
  <MFM_GuardSpotDirLeft>左侧</MFM_GuardSpotDirLeft>
  <MFM_GuardSpotDirRight>对</MFM_GuardSpotDirRight>
  <MFM_GuardSpotDirTop>返回顶部</MFM_GuardSpotDirTop>
  <MFM_GuardSpotDirBottom>底部</MFM_GuardSpotDirBottom>
  <MFM_USFMTitle>USFM</MFM_USFMTitle>
  <MFM_USFMMedievalTitle>钢铁联盟</MFM_USFMMedievalTitle>
  <MFM_MedievalHireRent>雇佣/租赁</MFM_MedievalHireRent>
  <MFM_MedievalHireRentDesc>雇佣或租借钢铁联盟的雇佣兵</MFM_MedievalHireRentDesc>
  <MFM_GuardMode>守卫模式</MFM_GuardMode>
  <MFM_GuardModeDesc>允许在守卫点自动分配单位</MFM_GuardModeDesc>
  <MFM_GuardSpotAffectedPawn>受影响的守卫 : {0}</MFM_GuardSpotAffectedPawn>
  <MFM_GuardSpotClearAffectedPawn>取消预订</MFM_GuardSpotClearAffectedPawn>
  <MFM_GuardSpotAffectGuard>强迫守护者</MFM_GuardSpotAffectGuard>
  <MFM_GuardSpotAffectGuardDesc>在此守卫点保留一名守卫</MFM_GuardSpotAffectGuardDesc>
  <MFM_Fired>开火！</MFM_Fired>
  <MFM_FiredDesc>允许您在四重奏结束前终止该雇佣兵的合同。请注意，在这种情况下，{0}会因为您不遵守合同而保留您的担保。</MFM_FiredDesc>
  <MFM_ClearDiscount>清除折扣</MFM_ClearDiscount>
  <MFM_GuardAttackOnlyNearThreats>只有近距离威胁</MFM_GuardAttackOnlyNearThreats>
  <MFM_GuardAttackOnlyNearThreatsDesc>如果启用，您可以指定哪些保镖只攻击非常接近的威胁。</MFM_GuardAttackOnlyNearThreatsDesc>
  <MFM_GuardStopAll>停止所有保镖</MFM_GuardStopAll>
  <MFM_GuardStopAllDesc>允许您停止所有保镖保护该单位。</MFM_GuardStopAllDesc>
  <MFM_GuardStop>停止保镖</MFM_GuardStop>
  <MFM_GuardStopDesc>允许您阻止保镖保护该单位。</MFM_GuardStopDesc>
  <MFM_Guard>保护单位</MFM_Guard>
  <MFM_GuardDesc>允许您向雇佣兵指定要保护的单位。这将使他们跟随并保护该单位。</MFM_GuardDesc>
  <!-- Confirm Dialogs -->
  <MFM_DialogConfirmFired>提前终止合同</MFM_DialogConfirmFired>
  <MFM_DialogConfirmFiredDesc>你真的想解雇这个雇佣兵吗？他的担保将由 {0} 保留。</MFM_DialogConfirmFiredDesc>
  <MFM_DialogConfirmPowerBeam>轨道光束发射</MFM_DialogConfirmPowerBeam>
  <MFM_DialogConfirmPowerBeamDesc>在选定的坐标上，从围绕你的星球运行的 USFM 卫星上发射轨道光束将花费你{0}银币，并需要 10 秒钟才能到达目标，你确认操作吗？</MFM_DialogConfirmPowerBeamDesc>
  <MFM_DialogConfirmCancelBill>丢弃法案</MFM_DialogConfirmCancelBill>
  <MFM_DialogConfirmCancelBillDesc>警告！如果您拒绝支付账单，您目前与{0}的所有合同都将被取消（包括雇佣的佣兵和租用的佣兵）。您愿意确认吗？</MFM_DialogConfirmCancelBillDesc>
  <MFM_ChoiceLetterCounterOfferTitle>还价</MFM_ChoiceLetterCounterOfferTitle>
  <MFM_ChoiceLetterCounterOffer>某派系开出了{0}银币的优厚报酬，让你的雇佣兵攻击你的殖民地。您的一些雇佣兵可能会接受他们的提议，但也有一些雇佣兵可能会因此与您反目成仇。他们要求你向他们支付{1}银币（直接转入他们的 USFM 账户），以便继续站在你这边，并有可能避免这次攻击。您有{2}个小时的时间来支付。</MFM_ChoiceLetterCounterOffer>
  <MFM_AddPawnRecall>将殖民者加入召回名单</MFM_AddPawnRecall>
  <MFM_AddPawn>添加殖民者</MFM_AddPawn>
  <MFM_RemovePawn>删除殖民者</MFM_RemovePawn>
  <MFM_ThisCurrentMap>当前地图 ({0})</MFM_ThisCurrentMap>
  <MFM_GuaranteeLineOK>{0}为 {1} 的保证。</MFM_GuaranteeLineOK>
  <MFM_GuaranteeLineNOK>{0}保证{1}（{2}-{3}，因为他受伤了）</MFM_GuaranteeLineNOK>
  <!-- Colors -->
  <MFM_ColorRed>红色</MFM_ColorRed>
  <MFM_ColorBlue>蓝色</MFM_ColorBlue>
  <MFM_ColorPurple>紫色</MFM_ColorPurple>
  <MFM_ColorGreen>绿色</MFM_ColorGreen>
  <MFM_ColorYellow>黄色</MFM_ColorYellow>
  <MFM_ColorOrange>橙色</MFM_ColorOrange>
  <MFM_ColorBlack>黑体</MFM_ColorBlack>
  <MFM_ColorGray>灰色</MFM_ColorGray>
  <MFM_ColorPink>粉红色</MFM_ColorPink>
  <MFM_ColorWhite>白色</MFM_ColorWhite>
  <MFM_ColorCyan>青色</MFM_ColorCyan>
  <!-- Alerts-->
  <MFM_AlertPlannedMercDelivery>订购的雇佣兵将在 {0} 到达。</MFM_AlertPlannedMercDelivery>
  <MFM_AlertPlannedMercDeliveryDesc>订购的雇佣兵将在截止日期前到达。</MFM_AlertPlannedMercDeliveryDesc>
  <MFM_AlertPlannedMercReturn>租借殖民者的回归抵达{0}。</MFM_AlertPlannedMercReturn>
  <MFM_AlertPlannedMercReturnDesc>您的一些雇佣兵的合同已经结束，他们将在规定时间结束后返回您的殖民地。</MFM_AlertPlannedMercReturnDesc>
  <MFM_AlertPlannedDeliveryStuffAndGuarantee>担保和雇佣兵装备的交付到达 {0}。</MFM_AlertPlannedDeliveryStuffAndGuarantee>
  <MFM_AlertPlannedDeliveryStuffAndGuaranteeDesc>在您的合同结束后，{0}将为您恢复雇佣兵在离开前所拥有或穿戴的装备（如果有的话）。</MFM_AlertPlannedDeliveryStuffAndGuaranteeDesc>
  <MFM_AlertPlannedPowerBeamAt>在 {0} 中发射 USFM 轨道光束</MFM_AlertPlannedPowerBeamAt>
  <MFM_AlertPlannedMedievalCaravanDelivery>送货商队将在 {0} 到达。</MFM_AlertPlannedMedievalCaravanDelivery>
  <MFM_AlertPlannedMedievalCaravanDeliveryDesc>钢铁联盟的运货商队正在运送货物/金钱的途中</MFM_AlertPlannedMedievalCaravanDeliveryDesc>
  <!-- Letters-->
  <MFM_LetterRentedMercArrival>租借殖民者的回归</MFM_LetterRentedMercArrival>
  <MFM_LetterRentedMercArrivalDesc>您租借给{0}的一名移民正在返回您的殖民地。</MFM_LetterRentedMercArrivalDesc>
  <MFM_LetterMercArrival>雇佣兵的到来</MFM_LetterMercArrival>
  <MFM_LetterMercArrivalDesc>奉命而来的雇佣兵。</MFM_LetterMercArrivalDesc>
  <MFM_LetterUSFMRenewStock>{0}更新部队</MFM_LetterUSFMRenewStock>
  <MFM_LetterUSFMRenewStockDesc>{0}刚刚更新了它的雇佣兵部队。不要犹豫，去看看他们的新提议吧。</MFM_LetterUSFMRenewStockDesc>
  <MFM_LetterDepositRecovery>保证和恢复</MFM_LetterDepositRecovery>
  <MFM_LetterDepositRecoveryDesc>在{1}雇佣兵合同结束后，{0}物品和装备已归还，并有以下保证：{2}总计：{3}。</MFM_LetterDepositRecoveryDesc>
  <MFM_LetterRentedMercInjured>受伤的雇佣兵</MFM_LetterRentedMercInjured>
  <MFM_LetterRentedMercInjuredDesc>由于受伤（{1}失踪），{0}的合同已被取消。</MFM_LetterRentedMercInjuredDesc>
  <MFM_LetterRentedMercDeath>雇佣兵之死</MFM_LetterRentedMercDeath>
  <MFM_LetterRentedMercDeathDesc>我们很遗憾地向您宣布，{0}已于今日{1}在服役期间去世。</MFM_LetterRentedMercDeathDesc>
  <MFM_LetterRentedMercDeathDescComp>他的尸体将被送还给你。</MFM_LetterRentedMercDeathDescComp>
  <MFM_LetterRentedMercEarnMoney>任务战利品</MFM_LetterRentedMercEarnMoney>
  <MFM_LetterRentedMercEarnMoneyDesc>在成功突袭一个基地后，{0}获得了奖金（{1}），他通过{2}将奖金发给你。</MFM_LetterRentedMercEarnMoneyDesc>
  <MFM_LetterMercRaid>雇佣兵突袭</MFM_LetterMercRaid>
  <MFM_LetterMercRaidDesc>{0}为{1}雇佣兵小队剿灭你付出了高昂的代价。</MFM_LetterMercRaidDesc>
  <MFM_LetterRentedMercPaid>{0}:雇佣兵报酬</MFM_LetterRentedMercPaid>
  <MFM_LetterRentedMercPaidDesc>收到来自{1}的{0}银币付款，与您雇佣的佣兵的活动收入相对应。</MFM_LetterRentedMercPaidDesc>
  <MFM_LetterMercFired>雇佣兵被解雇</MFM_LetterMercFired>
  <MFM_LetterMercFiredDesc>{0}在与{1}客户的一次任务中行为不端，对他的同事傲慢无礼，行为不当。因此，他被解雇了，并且暂时不能再被雇佣。</MFM_LetterMercFiredDesc>
  <MFM_LetterMercSalaryIncreaseRejected>流氓雇佣兵</MFM_LetterMercSalaryIncreaseRejected>
  <MFM_LetterMercSalaryIncreaseRejectedDesc>在您拒绝接受您的雇佣兵提出的加薪要求后，他们中的 {0} 加入了派别 {1}的阵营，现在将攻击您</MFM_LetterMercSalaryIncreaseRejectedDesc>
  <MFM_ChoiceLetterMercWantJoinTitle>雇佣兵想加入你的殖民地</MFM_ChoiceLetterMercWantJoinTitle>
  <MFM_ChoiceLetterMercWantJoin>{0}希望加入你的殖民地，但是{1}的规定是，要招募一名雇佣兵，你必须支付{2}倍于他的工资（{3}），总计{4}。</MFM_ChoiceLetterMercWantJoin>
  <MFM_LetterDiscount>{0}折扣</MFM_LetterDiscount>
  <MFM_LetterFirstDiscount>亲爱的客户，对于您的第一份佣兵订单，使用促销代码可获得 -{0}% 的折扣：{1}.</MFM_LetterFirstDiscount>
  <MFM_LetterDiscountDesc>亲爱的客户，下一次订购佣兵时，请使用促销代码获得 -{0}% 的折扣：{1}.</MFM_LetterDiscountDesc>
  <MFM_DiscountCodeWarning>请注意此代码，它不会被再次传播。</MFM_DiscountCodeWarning>
  <MFM_LetterMercPartRemovingExplosion>USFM 远程芯片爆炸</MFM_LetterMercPartRemovingExplosion>
  <MFM_LetterMercPartRemovingExplosionDesc>USFM 的自主远程监督系统（A.R.S.S）（得益于植入雇佣兵所有器官的芯片）检测到有人试图窃取其中一个器官，并触发了植入芯片的自毁装置。</MFM_LetterMercPartRemovingExplosionDesc>
  <MFM_LetterArrivedMedievalCaravanDelivery>运货商队</MFM_LetterArrivedMedievalCaravanDelivery>
  <MFM_LetterArrivedMedievalCaravanDeliveryRentedMercSilver>大篷车抵达，为您带来当前四分区租用的雇佣兵的工资</MFM_LetterArrivedMedievalCaravanDeliveryRentedMercSilver>
  <MFM_LetterRentedSlaveMercEscape>奴隶佣兵逃跑</MFM_LetterRentedSlaveMercEscape>
  <MFM_LetterRentedSlaveMercEscapeDesc>您租用的奴隶雇佣兵{0}在{1}执行任务时趁机逃跑。根据合同条款的规定，{2}将向您支付 2 倍于他的工资，以弥补您的损失。</MFM_LetterRentedSlaveMercEscapeDesc>
  <MFM_LetterRentedSlaveMercFactionRelationDecrease>派系关系惩罚</MFM_LetterRentedSlaveMercFactionRelationDecrease>
  <MFM_LetterRentedSlaveMercFactionRelationDecreaseDesc>派别{0}在与{1}交谈后发现，您的雇佣兵在国内执行任务时实行奴隶制，这有悖于他们的道德原则，因此会降低他们与您的关系。</MFM_LetterRentedSlaveMercFactionRelationDecreaseDesc>
  <MFM_LetterImprisonedMercPayment>{0}:被囚禁佣兵的报酬</MFM_LetterImprisonedMercPayment>
  <MFM_LetterImprisonedMercPaymentDesc>收到来自{1}的{0}银币付款，与释放被囚禁的雇佣兵相对应。</MFM_LetterImprisonedMercPaymentDesc>
  <!-- Messages -->
  <MFM_MsgCannotBeRentedAsMercBecauseBadHealth>{0}无法租用为雇佣兵，因为他无法行走（倒地）或其健康状况不足以提供服务</MFM_MsgCannotBeRentedAsMercBecauseBadHealth>
  <MFM_MsgPawnCannotBeRentedAsMerc>{0}不能被租用为雇佣兵，要么因为他不能战斗，要么因为他拥有与这一工作不相容的特征（纵火狂、裸体主义者等......）。</MFM_MsgPawnCannotBeRentedAsMerc>
  <MFM_MsgPawnBeRentedAsMercInvalidType>{0}不能胜任这项工作，因为他没有能力......！</MFM_MsgPawnBeRentedAsMercInvalidType>
  <MFM_MsgCannotBeRentedAsMercBecauseFired>{0}因其不良行为被{1}解雇，他可以在{2}中重新受雇。</MFM_MsgCannotBeRentedAsMercBecauseFired>
  <MFM_MsgNotEnoughtSilverPowerBeam>由于您没有足够的资金发射轨道光束，行动取消。</MFM_MsgNotEnoughtSilverPowerBeam>
  <MFM_MsgCannotBannishMercenary>您不能封禁雇佣兵。</MFM_MsgCannotBannishMercenary>
  <MFM_MsgCannotDropWeaponDuringCounterOffer>{0} 不想掉落/装备武器/装备（还价事件正在进行中）</MFM_MsgCannotDropWeaponDuringCounterOffer>
  <MFM_MsgPawnCannotBeRentedAsMerc2>{0}不能被租用为雇佣兵，因为他具有与此工作不相容的特征（纵火狂、裸体主义者等......）。</MFM_MsgPawnCannotBeRentedAsMerc2>
  <MFM_MsgMissingJobOnSomeColonistToRent>部分选定殖民者的工作缺失</MFM_MsgMissingJobOnSomeColonistToRent>
  <MFM_MsgToPayBillNeedCaravanOnSiteOfPayment>要支付账单，您必须在支付点上部署一支大篷车，并携带所需的资金。</MFM_MsgToPayBillNeedCaravanOnSiteOfPayment>
  <MFM_NeedSilverInCaravanPayBill>放在付款点的商队中没有足够的钱，您必须有 {0} 才能付账</MFM_NeedSilverInCaravanPayBill>
  <MFM_MsgNeedSelectMercToContinue>您需要选择至少一个雇佣兵才能继续</MFM_MsgNeedSelectMercToContinue>
  <MFM_MsgMustHaveTraitInBlacklistedTraits>必须删除特质{0}，因为它也存在于黑名单特质中！</MFM_MsgMustHaveTraitInBlacklistedTraits>
  <MFM_MsgPawnCannotBeRentedAsMercBecauseMissingTrait>{0}不能被租用为雇佣兵，因为他/她不具备 "必须具备的特征"{0}。</MFM_MsgPawnCannotBeRentedAsMercBecauseMissingTrait>
  <!-- jobs -->
  <MFM_Artist>艺术家</MFM_Artist>
  <MFM_Builder>建造者</MFM_Builder>
  <MFM_Cooker>炊具</MFM_Cooker>
  <MFM_Farmer>农民</MFM_Farmer>
  <MFM_Medical>医生</MFM_Medical>
  <MFM_Melee>近战士兵</MFM_Melee>
  <MFM_Ranged>远程士兵</MFM_Ranged>
  <MFM_Miner>矿工</MFM_Miner>
  <MFM_Scientist>科学家</MFM_Scientist>
  <MFM_Speak>外交官</MFM_Speak>
  <MFM_Tech>技术人员</MFM_Tech>
  <MFM_Trainer>驯兽师</MFM_Trainer>
  <MFM_Clean>清洁器</MFM_Clean>
  <MFM_Carry>搬运工</MFM_Carry>
  <MFM_Civil>民间</MFM_Civil>
  <MFM_Recruit>招募</MFM_Recruit>
  <MFM_Confirmed>士兵</MFM_Confirmed>
  <MFM_Veteran>老兵</MFM_Veteran>
  <MFM_Elite>精英</MFM_Elite>
  <MFM_Cyborg>指挥官</MFM_Cyborg>
  <MFM_WantedRecruit>招募 ({0}/{1})</MFM_WantedRecruit>
  <MFM_WantedConfirmed>士兵 ({0}/{1})</MFM_WantedConfirmed>
  <MFM_WantedVeteran>老兵 ({0}/{1})</MFM_WantedVeteran>
  <MFM_WantedElite>精英 ({0}/{1})</MFM_WantedElite>
  <MFM_WantedCyborg>指挥官 ({0}/{1})</MFM_WantedCyborg>
  <MFM_Gear0>无装备（免费，基本 USFM 衬衫，简单裤子）</MFM_Gear0>
  <MFM_Gear1>基本（成本{0}：防弹背心 简单头盔）</MFM_Gear1>
  <MFM_Gear2>标准（成本{0}：板甲高级头盔）</MFM_Gear2>
  <MFM_Gear3>高级（成本{0}：海洋装甲动力装甲头盔）</MFM_Gear3>
  <MFM_Weapon0>无武器</MFM_Weapon0>
  <MFM_Weapon1>基本（成本{0}：手枪/机关枪或刀/棍/伊卡瓦）</MFM_Weapon1>
  <MFM_Weapon2>标准（成本{0}：重型 SMG/Chain Shotgun 或 Gladius）</MFM_Weapon2>
  <MFM_Weapon3>高级（成本{0}：突击步枪/冲锋枪/狙击枪或长剑）</MFM_Weapon3>
  <MFM_Weapon4>世界末日（成本{0}：三联装火箭/末日火箭发射器或重型号角）</MFM_Weapon4>
  <MFM_Gear0Medieval>无装备（免费，Tribalwear）</MFM_Gear0Medieval>
  <MFM_Gear1Medieval>基本（成本{0}：衬衫 简单裤子 战争面具）</MFM_Gear1Medieval>
  <MFM_Gear2Medieval>标准（成本{0}：派克大衣（Parka） 简易裤子（Simple Pants） 简易头盔（Simple Helmet</MFM_Gear2Medieval>
  <MFM_Gear3Medieval>高级（成本{0}：板甲高级头盔）</MFM_Gear3Medieval>
  <MFM_Weapon1Medieval>基础（成本{0}：短弓或刀/棍/伊卡瓦）</MFM_Weapon1Medieval>
  <MFM_Weapon2Medieval>标准（成本{0}：大弓或格拉迪乌斯）</MFM_Weapon2Medieval>
  <MFM_Weapon3Medieval>高级（成本{0}：弯弓或长剑）</MFM_Weapon3Medieval>
  <MFM_TransportFee>运输费</MFM_TransportFee>
  <MFM_ImmediateDelivery>立即交付（每个雇佣兵的成本为 {0}</MFM_ImmediateDelivery>
  <MFM_QuickDelivery>快速交货（每个雇佣兵成本{0}，交货时间在{1}小时到{2}小时之间）</MFM_QuickDelivery>
  <MFM_StandardDelivery>标准配送（免费，{0}小时至{1}小时内送达）</MFM_StandardDelivery>
  <MFM_HireMerc>雇佣军</MFM_HireMerc>
  <MFM_RentMerc>出租雇佣兵</MFM_RentMerc>
  <MFM_PowerBeam>轨道瞄准</MFM_PowerBeam>
  <MFM_GuardJob>(守卫 {0})</MFM_GuardJob>
  <MFM_Guarantee>保证 : {0}</MFM_Guarantee>
  <MFM_Shipping>运输 : {0}</MFM_Shipping>
  <MFM_Prorata>优先级 ：{0}</MFM_Prorata>
  <MFM_Discount>折扣 : -{0}%</MFM_Discount>
  <MFM_RecoverableGuarantee>可收回担保 : {0}</MFM_RecoverableGuarantee>
  <MFM_StuffCost>东西 : {0}</MFM_StuffCost>
  <MFM_Count>雇佣兵 : {0}</MFM_Count>
  <MFM_ImmediateCost>即时成本 : {0}</MFM_ImmediateCost>
  <MFM_CostPerMonth>每个四面体的成本 : {0}</MFM_CostPerMonth>
  <MFM_IncomeThisMonth>收入此四部曲 : {0}</MFM_IncomeThisMonth>
  <MFM_Income>每个四面体的收入 : {0}</MFM_Income>
  <MFM_Recall>回顾 : {0}</MFM_Recall>
  <MFM_QuadBillShowIncome>显示收入</MFM_QuadBillShowIncome>
  <MFM_QuadBillShowCost>显示费用</MFM_QuadBillShowCost>
  <MFM_QuadBillMercListHiredPendingOrder>{0} 雇佣兵（每四面体成本={1})</MFM_QuadBillMercListHiredPendingOrder>
  <MFM_QuadBillMercListHired>{0} ({1} ({2}/20), salary={3}{4})</MFM_QuadBillMercListHired>
  <MFM_QuadBillMercListHiredNotHappy>{0}（{1}（{2}/20），工资={3}（{4}最初，{5}%因为不开心））。</MFM_QuadBillMercListHiredNotHappy>
  <MFM_QuadBillMercListHiredHappy>{0} ({1} ({2}/20), salary={3} ({4} initially, -{5}% because happy))</MFM_QuadBillMercListHiredHappy>
  <MFM_QuadBillMercListRented>{0} ({1} ({2}/20), salary={3})</MFM_QuadBillMercListRented>
  <MFM_QuadBillGuaranteePart>保证 = {0}、</MFM_QuadBillGuaranteePart>
  <MFM_QuadBillIncome>收入 : {0}</MFM_QuadBillIncome>
  <MFM_QuadBillCost>成本 : {0}</MFM_QuadBillCost>
  <MFM_QuadBillTotal>总计 : {0}</MFM_QuadBillTotal>
  <MFM_QuadBillTotalSummarize>每四面体总计 : {0}</MFM_QuadBillTotalSummarize>
  <MFM_QuadBillCountRentedMerc>出租佣兵 : {0}</MFM_QuadBillCountRentedMerc>
  <MFM_QuadBillCountHiredMerc>雇佣军 : {0}</MFM_QuadBillCountHiredMerc>
  <MFM_Bill>{0} 比尔</MFM_Bill>
  <MFM_Job>工作 : {0}</MFM_Job>
  <MFM_Salary>薪资 : {0}</MFM_Salary>
  <MFM_Level>等级 : {0}</MFM_Level>
  <MFM_Affinity>亲和力 : {0}</MFM_Affinity>
  <MFM_GuaranteeCS>保证 : {0}% ( {1}/{2} )</MFM_GuaranteeCS>
  <MFM_FiredCountDown>从 {0} 被解雇，剩余时间 : {1}</MFM_FiredCountDown>
  <MFM_AffinityOK>好的</MFM_AffinityOK>
  <MFM_AffinityNeutral>中性</MFM_AffinityNeutral>
  <MFM_AffinityBad>坏</MFM_AffinityBad>
  <!-- Settings -->
  <MFM_SettingsResetBlacklistedTraits>重置黑名单</MFM_SettingsResetBlacklistedTraits>
  <MFM_SettingsResetBlacklistedPawnKind>重置黑名单中的棋子种类</MFM_SettingsResetBlacklistedPawnKind>
  <MFM_SettingsResetHediffToKeepOnMercGen>重置 hediff defName 保留</MFM_SettingsResetHediffToKeepOnMercGen>
  <MFM_SettingsResetBlacklistedWeapons>重置黑名单武器</MFM_SettingsResetBlacklistedWeapons>
  <MFM_SettingsResetMustHaveTraits>重置必须具备的特质</MFM_SettingsResetMustHaveTraits>
  <MFM_SettingsSectionGeneral>一般内容</MFM_SettingsSectionGeneral>
  <MFM_SettingsSectionNbMercenaries>按等级划分的雇佣兵可用性</MFM_SettingsSectionNbMercenaries>
  <MFM_SettingsSectionMercPrice>雇佣兵价格</MFM_SettingsSectionMercPrice>
  <MFM_SettingsSectionTransport>运输设置</MFM_SettingsSectionTransport>
  <MFM_SettingsSectionBlacklistedTraits>雇佣兵黑名单特质（defName）</MFM_SettingsSectionBlacklistedTraits>
  <MFM_SettingsSectionIncidents>事件</MFM_SettingsSectionIncidents>
  <MFM_SettingsSectionBlacklistedPawnKind>不允许生成佣兵的 PawnKind（defName）</MFM_SettingsSectionBlacklistedPawnKind>
  <MFM_SettingsSectionHediffToKeepOnMercGen>Hediff (defName) 以保持雇佣兵的生成</MFM_SettingsSectionHediffToKeepOnMercGen>
  <MFM_SettingsSectionBlacklistedWeapons>雇佣兵一代不允许使用的武器（defName）</MFM_SettingsSectionBlacklistedWeapons>
  <MFM_SettingsSectionMedievalMode>中世纪模式</MFM_SettingsSectionMedievalMode>
  <MFM_SettingsSectionMustHaveTraits>必须具备的特质（特质程度标签）</MFM_SettingsSectionMustHaveTraits>
  <MFM_SettingsDisableNotifWhenDisusedMercDie>废弃佣兵被杀时禁用通知</MFM_SettingsDisableNotifWhenDisusedMercDie>
  <MFM_SettingsPercentDisusedMercCanDiePerQuad>在四分区的每个起点可以杀死的废弃佣兵百分比 ({0}%)</MFM_SettingsPercentDisusedMercCanDiePerQuad>
  <MFM_SettingsTimeBeforeRenewOffers>在 USFM 更新这些提议之前的时间 ({0})</MFM_SettingsTimeBeforeRenewOffers>
  <MFM_SettingsHideIcon>隐藏雇佣兵图标</MFM_SettingsHideIcon>
  <MFM_SettingsHideLevel>隐藏雇佣兵等级</MFM_SettingsHideLevel>
  <MFM_SettingsPriceRecruit>基本价格 招募</MFM_SettingsPriceRecruit>
  <MFM_SettingsPriceConfirmed>底价兵</MFM_SettingsPriceConfirmed>
  <MFM_SettingsPriceVeteran>基本价格 老兵</MFM_SettingsPriceVeteran>
  <MFM_SettingsPriceElite>底价精英</MFM_SettingsPriceElite>
  <MFM_SettingsPriceCyborg>底价指挥官</MFM_SettingsPriceCyborg>
  <MFM_SettingsGuaranteeRecruit>保证招募</MFM_SettingsGuaranteeRecruit>
  <MFM_SettingsGuaranteeConfirmed>担保兵</MFM_SettingsGuaranteeConfirmed>
  <MFM_SettingsGuaranteeVeteran>保证老兵</MFM_SettingsGuaranteeVeteran>
  <MFM_SettingsGuaranteeElite>保证精英</MFM_SettingsGuaranteeElite>
  <MFM_SettingsGuaranteeCyborg>保证指挥官</MFM_SettingsGuaranteeCyborg>
  <MFM_SettingsMinRecruit>最低招募人数 ({0})</MFM_SettingsMinRecruit>
  <MFM_SettingsMaxRecruit>最大招募人数 ({0})</MFM_SettingsMaxRecruit>
  <MFM_SettingsMinConfirmed>最低兵力 ({0})</MFM_SettingsMinConfirmed>
  <MFM_SettingsMaxConfirmed>最大兵力 ({0})</MFM_SettingsMaxConfirmed>
  <MFM_SettingsMinVeteran>最小老兵 ({0})</MFM_SettingsMinVeteran>
  <MFM_SettingsMaxVeteran>最大老兵 ({0})</MFM_SettingsMaxVeteran>
  <MFM_SettingsMinElite>最低精英 ({0})</MFM_SettingsMinElite>
  <MFM_SettingsMaxElite>最大精英 ({0})</MFM_SettingsMaxElite>
  <MFM_SettingsMinCyborg>最低指挥官 ({0})</MFM_SettingsMinCyborg>
  <MFM_SettingsMaxCyborg>最高指挥官 ({0})</MFM_SettingsMaxCyborg>
  <MFM_SettingsTransportStandardMinHour>标准交付最短小时 ({0}h)</MFM_SettingsTransportStandardMinHour>
  <MFM_SettingsTransportStandardMaxHour>标准交付最长时间 ({0}h)</MFM_SettingsTransportStandardMaxHour>
  <MFM_SettingsTransportQuickMinHour>快速交付的最短时间 ({0}h)</MFM_SettingsTransportQuickMinHour>
  <MFM_SettingsTransportQuickMaxHour>快速交付最长时间 ({0}h)</MFM_SettingsTransportQuickMaxHour>
  <MFM_SettingsTransportQuickPrice>快速交货单价</MFM_SettingsTransportQuickPrice>
  <MFM_SettingsTransportImmediatePrice>即时交付单价</MFM_SettingsTransportImmediatePrice>
  <MFM_SettingsBadMoodNbhPerQuadFloor>雇佣兵在四分区中心情不好影响每月费用的小时数 ({0}h)</MFM_SettingsBadMoodNbhPerQuadFloor>
  <MFM_SettingsGoodMoodNbhPerQuadFloor>佣兵们在一个四分区中心情好到影响每月费用的小时数（{0}h）</MFM_SettingsGoodMoodNbhPerQuadFloor>
  <MFM_SettingsBadMoodCoefIncCost>达到坏情绪上限时的每月费用增加系数 ({0}%}</MFM_SettingsBadMoodCoefIncCost>
  <MFM_SettingsGoodMoodCoefDecCost>达到坏情绪上限时每月费用的下降系数 ({0}%)</MFM_SettingsGoodMoodCoefDecCost>
  <MFM_SettingsStuffAndGuaranteeDeliveryTimeMin>交付物品和保证的最短时间 ({0}h)</MFM_SettingsStuffAndGuaranteeDeliveryTimeMin>
  <MFM_SettingsStuffAndGuaranteeDeliveryTimeMax>交付物品和保证的最长时间 ({0}h)</MFM_SettingsStuffAndGuaranteeDeliveryTimeMax>
  <MFM_SettingsPriceGear1>基本装备包价格</MFM_SettingsPriceGear1>
  <MFM_SettingsPriceGear2>标准装备包价格</MFM_SettingsPriceGear2>
  <MFM_SettingsPriceGear3>高级装备包价格</MFM_SettingsPriceGear3>
  <MFM_SettingsPriceWeapon1>基本武器价格</MFM_SettingsPriceWeapon1>
  <MFM_SettingsPriceWeapon2>标准武器价格</MFM_SettingsPriceWeapon2>
  <MFM_SettingsPriceWeapon3>高级武器的价格</MFM_SettingsPriceWeapon3>
  <MFM_SettingsPriceWeapon4>末日武器的价格</MFM_SettingsPriceWeapon4>
  <MFM_SettingsUseOnlyVanillaForWeapon>佣兵只能使用香草武器</MFM_SettingsUseOnlyVanillaForWeapon>
  <MFM_SettingsUseOnlyVanillaForGear>佣兵只能使用香草齿轮</MFM_SettingsUseOnlyVanillaForGear>
  <MFM_SettingsUSFMSuspendedMinTime>来自 USFM 的最短暂停时间 ({0})</MFM_SettingsUSFMSuspendedMinTime>
  <MFM_SettingsUSFMSuspendedMaxTime>来自 USFM 的最长暂停时间 ({0})</MFM_SettingsUSFMSuspendedMaxTime>
  <MFM_SettingsPowerBeamCost>发射轨道光束的成本</MFM_SettingsPowerBeamCost>
  <MFM_SettingsMercJoinNbSalary>雇佣兵想要加入殖民地：支付薪水的次数 ({0})</MFM_SettingsMercJoinNbSalary>
  <MFM_SettingsDiscountMin>USFM 最低折扣 ({0}%)</MFM_SettingsDiscountMin>
  <MFM_SettingsDiscountMax>USFM 最大折扣 ({0}%)</MFM_SettingsDiscountMax>
  <MFM_SettingsIncidentEnable>启用此事件</MFM_SettingsIncidentEnable>
  <MFM_SettingsIncidentsCounterOfferMinPrice>请求加薪的最低比率 ({0}%)</MFM_SettingsIncidentsCounterOfferMinPrice>
  <MFM_SettingsIncidentsCounterOfferMaxPrice>加薪申请的最高比率 ({0}%)</MFM_SettingsIncidentsCounterOfferMaxPrice>
  <MFM_SettingsIncidentsCounterOffer>还价</MFM_SettingsIncidentsCounterOffer>
  <MFM_SettingsIncidentsRaid>雇佣兵突袭</MFM_SettingsIncidentsRaid>
  <MFM_SettingsCyborgBionicSource>指挥官雇佣兵仿生 MOD 源代码</MFM_SettingsCyborgBionicSource>
  <MFM_SettingsRiskRemovedCyborgPartExplode>移除属于 USFM 的仿生肢体将导致爆炸的风险 ({0}%)</MFM_SettingsRiskRemovedCyborgPartExplode>
  <MFM_SettingsMinAge>雇佣兵最低年龄 ({0})</MFM_SettingsMinAge>
  <MFM_SettingsMaxAge>雇佣兵年龄上限 ({0})</MFM_SettingsMaxAge>
  <MFM_SettingsMinXPGainPerDayRentedMerc>租用雇佣兵每天获得的最低 XP 值</MFM_SettingsMinXPGainPerDayRentedMerc>
  <MFM_SettingsMaxXPGainPerDayRentedMerc>租用佣兵每天可获得的最高 XP 值</MFM_SettingsMaxXPGainPerDayRentedMerc>
  <MFM_SettingsAllowNonViolentToBeRent>允许将非暴力殖民者租借给 USFM</MFM_SettingsAllowNonViolentToBeRent>
  <MFM_SettingsMedievalModeDeliveryCaravanMinTime>送货商队的最短到达时间 ({0}h)</MFM_SettingsMedievalModeDeliveryCaravanMinTime>
  <MFM_SettingsMedievalModeDeliveryCaravanMaxTime>送货商队的最长抵达时间（{0}小时）</MFM_SettingsMedievalModeDeliveryCaravanMaxTime>
  <MFM_SettingsCurrentEpoch>纪元</MFM_SettingsCurrentEpoch>
  <MFM_SettingsCurrentEpochAuto>自动翻译</MFM_SettingsCurrentEpochAuto>
  <MFM_SettingsCurrentEpochMedieval>中世纪</MFM_SettingsCurrentEpochMedieval>
  <MFM_SettingsCurrentEpochModern>现代</MFM_SettingsCurrentEpochModern>
  <MFM_SettingsCurrentEpochModernOnly>仅限现代（将删除钢铁联盟）</MFM_SettingsCurrentEpochModernOnly>
  <MFM_SettingsMercSlaveIncomeDecrease>奴隶佣兵，收入减少 (-{0}%)</MFM_SettingsMercSlaveIncomeDecrease>
  <MFM_SettingsPreventNonMercSpawnWithUSFMStuff>防止非雇佣兵小兵生成 USFM 的东西</MFM_SettingsPreventNonMercSpawnWithUSFMStuff>
  <MFM_SettingsSalaryDecreaseRateAppliedToRentedMerc>适用于租用佣兵的正常减少百分比 (-{0}%)</MFM_SettingsSalaryDecreaseRateAppliedToRentedMerc>
  <MFM_SettingsBuyMercSalaryMultiplier>当玩家要购买雇佣兵时适用的工资乘数 (x{0})</MFM_SettingsBuyMercSalaryMultiplier>
  <MFM_SettingsAllowMercNonZeroOtherSkills>允许雇佣兵的其他技能不为零（总是低于主要技能）</MFM_SettingsAllowMercNonZeroOtherSkills>
  <MFM_SettingsImprisonedMercenariesAreNoLongerMerc>被逮捕的雇佣兵不再被视为雇佣兵</MFM_SettingsImprisonedMercenariesAreNoLongerMerc>
  <MFM_SettingsSetBasicWorkTypeToOne>将雇佣的佣兵的基本工作类型优先级设为 1（消防员、病人、PatientBedRest）</MFM_SettingsSetBasicWorkTypeToOne>
</LanguageData>
